neat_ml/__init__.py
neat_ml/cli.py
neat_ml/graph_embedding/__init__.py
neat_ml/graph_embedding/graph_embedding.py
neat_ml/link_prediction/__init__.py
neat_ml/link_prediction/mlp_model.py
neat_ml/link_prediction/model.py
neat_ml/link_prediction/sklearn_model.py
neat_ml/pre_run_checks/__init__.py
neat_ml/pre_run_checks/pre_run_checks.py
neat_ml/run_classifier/__init__.py
neat_ml/run_classifier/run_classifier.py
neat_ml/update_yaml/__init__.py
neat_ml/update_yaml/update_yaml.py
neat_ml/upload/__init__.py
neat_ml/upload/upload.py
neat_ml/visualization/__init__.py
neat_ml/visualization/visualization.py
neat_ml/yaml_helper/__init__.py
neat_ml/yaml_helper/yaml_helper.py
neat_ml-0.1.0.dist-info/LICENSE
neat_ml-0.1.0.dist-info/METADATA
neat_ml-0.1.0.dist-info/WHEEL
neat_ml-0.1.0.dist-info/entry_points.txt
neat_ml-0.1.0.dist-info/top_level.txt
neat_ml-0.1.0.dist-info/RECORD
