Metadata-Version: 2.1
Name: neat-ml
Version: 0.1.0
Summary: Neural-network Embedding All the Things
Home-page: https://github.com/Knowledge-Graph-Hub/neat_ml
Author: Deepak Unni, Justin Reese, J. Harry Caufield, Harshad Hegde
Author-email: deepak.unni3@lbl.gov, justaddcoffee+github@gmail.com, jhc@lbl.gov, hhegde@lbl.gov
License: BSD-3
Requires-Python: >=3.8
License-File: LICENSE
Requires-Dist: tqdm
Requires-Dist: click
Requires-Dist: pyyaml
Requires-Dist: sklearn
Requires-Dist: grape
Requires-Dist: opencv-python
Requires-Dist: numpy
Requires-Dist: pandas
Requires-Dist: transformers
Requires-Dist: boto3
Requires-Dist: botocore
Requires-Dist: validators
Requires-Dist: linkml
Requires-Dist: neat-ml-schema
Requires-Dist: linkml-validator
Provides-Extra: test
Requires-Dist: pytest ; extra == 'test'
Requires-Dist: pytest-cov ; extra == 'test'
Requires-Dist: coveralls ; extra == 'test'
Requires-Dist: validate-version-code ; extra == 'test'
Requires-Dist: codacy-coverage ; extra == 'test'
Requires-Dist: parameterized ; extra == 'test'
Requires-Dist: mypy ; extra == 'test'
